cubit/__init__.py
cubit/_base.py
cubit/physical_data.py
cubit/system.py
cubit/units.py
cubit-0.1.0.dist-info/LICENSE.txt
cubit-0.1.0.dist-info/WHEEL
cubit-0.1.0.dist-info/METADATA
cubit-0.1.0.dist-info/RECORD
